textual_tagset/__init__.py
textual_tagset/demo/__init__.py
textual_tagset/demo/__main__.py
textual_tagset/demo/basescreen.py
textual_tagset/demo/basescreen.tcss
textual_tagset/demo/data.py
textual_tagset/tagset.py
textual_tagset/tagset.tcss
textual_tagset-0.3.3.dist-info/METADATA
textual_tagset-0.3.3.dist-info/WHEEL
textual_tagset-0.3.3.dist-info/RECORD
