Metadata-Version: 2.3
Name: textual-tagset
Version: 0.3.3
Summary: Maintain tag sets easily and visually
License: MIT
Author: Steve Holden
Author-email: steve@holdenweb.com
Requires-Python: >=3.9,<4.0
Classifier: License :: OSI Approved :: MIT License
Classifier: Programming Language :: Python :: 3
Classifier: Programming Language :: Python :: 3.9
Classifier: Programming Language :: Python :: 3.10
Classifier: Programming Language :: Python :: 3.11
Classifier: Programming Language :: Python :: 3.12
Classifier: Programming Language :: Python :: 3.13
Requires-Dist: textual (>=1.0,<2.0)
Requires-Dist: textual-dev (>=1.2,<2.0)
